plasgate/__init__.py
plasgate/main.py
plasgate/test_package.py
plasgate/rest/__init__.py
plasgate-1.0.0.dist-info/METADATA
plasgate-1.0.0.dist-info/WHEEL
plasgate-1.0.0.dist-info/top_level.txt
plasgate-1.0.0.dist-info/RECORD
