Metadata-Version: 2.1
Name: plasgate
Version: 1.0.0
Summary: Helper library for working with tests
Home-page: UNKNOWN
License: UNKNOWN
Platform: UNKNOWN
